{
	"name": "main_pipeline",
	"properties": {
		"activities": [
			{
				"name": "Execute Pipeline1",
				"type": "ExecutePipeline",
				"dependsOn": [],
				"policy": {
					"secureInput": false
				},
				"userProperties": [],
				"typeProperties": {
					"pipeline": {
						"referenceName": "source_to_raw_div_cs1",
						"type": "PipelineReference"
					},
					"waitOnCompletion": true
				}
			},
			{
				"name": "Execute Pipeline2",
				"type": "ExecutePipeline",
				"dependsOn": [
					{
						"activity": "Execute Pipeline1",
						"dependencyConditions": [
							"Succeeded"
						]
					}
				],
				"policy": {
					"secureInput": false
				},
				"userProperties": [],
				"typeProperties": {
					"pipeline": {
						"referenceName": "raw_to_acq_2",
						"type": "PipelineReference"
					},
					"waitOnCompletion": true
				}
			},
			{
				"name": "Execute Pipeline3",
				"type": "ExecutePipeline",
				"dependsOn": [
					{
						"activity": "Execute Pipeline2",
						"dependencyConditions": [
							"Succeeded"
						]
					}
				],
				"policy": {
					"secureInput": false
				},
				"userProperties": [],
				"typeProperties": {
					"pipeline": {
						"referenceName": "Acq_to_enr_unh_div_cs1",
						"type": "PipelineReference"
					},
					"waitOnCompletion": true
				}
			}
		],
		"folder": {
			"name": "Divyanshi_Case_Study_1"
		},
		"annotations": [],
		"lastPublishTime": "2024-11-11T06:48:31Z"
	},
	"type": "Microsoft.DataFactory/factories/pipelines"
}